dark_swag/__init__.py
dark_swag/_example.py
dark_swag/dark_router.py
dark_swag/example.py
dark_swag/example2.py
dark_swag/example3.py
dark_swag/padlock_fix.py
dark_swag/utils.py
dark_swag/static/__init__.py
dark_swag/static/background_text.css.jinja2
dark_swag/static/dark.css.jinja2
dark_swag/static/dark_toggle.js
dark_swag/static/darkswag.svg
dark_swag/static/darkswag_color.svg
dark_swag/static/light.css.jinja2
dark_swag/static/light_toggle.js
dark_swag/static/logo.css.jinja2
dark_swag/static/massive_stylesheet.png
dark_swag/static/screenshot.png
dark_swag/static/screenshot2.png
dark_swag/static/screenshot3.png
dark_swag/static/screenshot4.png
dark_swag/static/swagger-ui-bundle.js
dark_swag/static/swagger-ui.css
dark_swag/static/swagger-ui.css.map
dark_swag/static/swagger-ui.js
dark_swag/static/swagger-ui.js.map
dark_swag/static/your_logo.svg
dark_swag/static/__pycache__/__init__.cpython-312.pyc
dark_swag/static/docs_images/auth_modal.png
dark_swag/static/docs_images/authorized.png
dark_swag/static/docs_images/background_text.png
dark_swag/static/docs_images/custom_logo.png
dark_swag/static/docs_images/custom_logo2.png
dark_swag/static/docs_images/docstring.png
dark_swag/static/docs_images/markdown.png
dark_swag/static/docs_images/massive_stylesheet.png
dark_swag/static/docs_images/schema.png
dark_swag/static/docs_images/toggle.png
dark_swag/static/docs_images/toggle_dark.png
dark_swag/static/docs_images/unauthorized.png
dark_swag/static/docs_images/whole_dark.png
dark_swag/static/docs_images/whole_light.png
dark_swag-1.0.2.dist-info/LICENSE
dark_swag-1.0.2.dist-info/METADATA
dark_swag-1.0.2.dist-info/WHEEL
dark_swag-1.0.2.dist-info/top_level.txt
dark_swag-1.0.2.dist-info/RECORD
