Metadata-Version: 2.1
Name: dark_swag
Version: 1.0.2
Summary: Dark mode Swagger for your FastAPI apps
Home-page: https://github.com/nebko16/dark_swag
Author: nebko16
Author-email: nebko16@gmail.com
License: GPL-3.0
Keywords: fastapi openapi swagger dark night darkmode dark-mode theme docs documentation
Requires-Python: >=3.6
License-File: LICENSE
Requires-Dist: fastapi
Requires-Dist: jinja2
Requires-Dist: python-multipart
